TOPSIS_Ayush_101803635
