Metadata-Version: 1.1
Name: Topsis-Ayush-101803635
Version: 0.0.2
Summary: myTopsisPackage
Home-page: UNKNOWN
Author: Ayush anand Saxena
Author-email: asaxena_be18@thapar.edu
License: MIT
Keywords: TOPSIS
Platform: UNKNOWN
Classifier: Development Status :: 5 - Production/Stable
Classifier: Intended Audience :: Education
Classifier: Operating System :: Microsoft :: Windows :: Windows 10
Classifier: License :: OSI Approved :: MIT License
Classifier: Programming Language :: Python :: 3
